setup.py
src/__init__.py
src/jsonformatter.py
src/json_formatter.egg-info/PKG-INFO
src/json_formatter.egg-info/SOURCES.txt
src/json_formatter.egg-info/dependency_links.txt
src/json_formatter.egg-info/requires.txt
src/json_formatter.egg-info/top_level.txt