Metadata-Version: 1.1
Name: json-formatter
Version: 0.1.0-alpha-20141128-1014-94cc025
Summary: A python library adding a json log formatter
Home-page: http://github.com/nikicat/python-json-logger
Author: Zakaria Zajac
Author-email: zak@madzak.com
License: BSD
Platform: UNKNOWN
Classifier: Development Status :: 3 - Alpha
Classifier: Intended Audience :: Developers
Classifier: License :: OSI Approved :: BSD License
Classifier: Operating System :: OS Independent
Classifier: Programming Language :: Python
Classifier: Programming Language :: Python :: 2
Classifier: Programming Language :: Python :: 3
Classifier: Topic :: System :: Logging
